odoo/addons/purchase_fop_shipping/README.rst
odoo/addons/purchase_fop_shipping/__init__.py
odoo/addons/purchase_fop_shipping/__manifest__.py
odoo/addons/purchase_fop_shipping/i18n/de.po
odoo/addons/purchase_fop_shipping/i18n/es.po
odoo/addons/purchase_fop_shipping/i18n/es_PE.po
odoo/addons/purchase_fop_shipping/i18n/fr.po
odoo/addons/purchase_fop_shipping/i18n/fr_BE.po
odoo/addons/purchase_fop_shipping/i18n/gl.po
odoo/addons/purchase_fop_shipping/i18n/hr.po
odoo/addons/purchase_fop_shipping/i18n/it.po
odoo/addons/purchase_fop_shipping/i18n/nl.po
odoo/addons/purchase_fop_shipping/i18n/nl_NL.po
odoo/addons/purchase_fop_shipping/i18n/pt_BR.po
odoo/addons/purchase_fop_shipping/i18n/purchase_fop_shipping.pot
odoo/addons/purchase_fop_shipping/i18n/ro.po
odoo/addons/purchase_fop_shipping/i18n/sl.po
odoo/addons/purchase_fop_shipping/i18n/vi_VN.po
odoo/addons/purchase_fop_shipping/models/__init__.py
odoo/addons/purchase_fop_shipping/models/partner.py
odoo/addons/purchase_fop_shipping/models/purchase.py
odoo/addons/purchase_fop_shipping/security/res_groups.xml
odoo/addons/purchase_fop_shipping/static/description/icon.png
odoo/addons/purchase_fop_shipping/tests/__init__.py
odoo/addons/purchase_fop_shipping/tests/test_fop_shipping.py
odoo/addons/purchase_fop_shipping/views/purchase_order.xml
odoo/addons/purchase_fop_shipping/views/res_partner.xml
odoo_addon_purchase_fop_shipping-18.0.1.0.1.1.dist-info/METADATA
odoo_addon_purchase_fop_shipping-18.0.1.0.1.1.dist-info/WHEEL
odoo_addon_purchase_fop_shipping-18.0.1.0.1.1.dist-info/top_level.txt
odoo_addon_purchase_fop_shipping-18.0.1.0.1.1.dist-info/RECORD
